AUTHORS
LICENSE
MANIFEST.in
README.rst
setup.py
apibee/__init__.py
apibee/client.py
apibee.egg-info/PKG-INFO
apibee.egg-info/SOURCES.txt
apibee.egg-info/dependency_links.txt
apibee.egg-info/not-zip-safe
apibee.egg-info/requires.txt
apibee.egg-info/top_level.txt
tests/bottle.py
tests/server.py
tests/test_client.py